cmot/__init__.py
cmot/sequence_statistics.py
cmot/version.py
cmot/collections/__init__.py
cmot/collections/circular_buffer.py
cmot-1.1.3.dist-info/LICENSE
cmot-1.1.3.dist-info/METADATA
cmot-1.1.3.dist-info/WHEEL
cmot-1.1.3.dist-info/entry_points.txt
cmot-1.1.3.dist-info/top_level.txt
cmot-1.1.3.dist-info/RECORD
