Metadata-Version: 2.1
Name: cmot
Version: 1.1.3
Summary: A collection of miscellaneous goods at an unbeatable price
Home-page: UNKNOWN
Author: Eric Langlois
Author-email: eric@langlois.xyz
License: MIT
Platform: UNKNOWN
Classifier: Intended Audience :: Developers
Classifier: License :: OSI Approved :: MIT License
Classifier: Operating System :: OS Independent
Classifier: Programming Language :: Python :: 3
Classifier: Topic :: Utilities
Requires-Python: >=3.8
